{
    "name": "input_model.pnml",
    "tasks": [
        "Activity K",
        "24",
        "29",
        "Activity I",
        "Activity N",
        "Activity F",
        "Activity S",
        "Activity A",
        "Activity T",
        "Activity U",
        "Activity J",
        "28",
        "Activity G",
        "27",
        "Activity R",
        "Activity E",
        "25",
        "Activity Q",
        "Activity H",
        "26",
        "Activity P",
        "Activity D",
        "Activity M",
        "Activity B",
        "23",
        "Activity L",
        "31",
        "Activity C",
        "Activity O"
    ],
    "constraints": [
        {
            "template": "Init",
            "parameters": [
                [
                    "Activity A"
                ]
            ]
        },
        {
            "template": "End",
            "parameters": [
                [
                    "Activity M"
                ]
            ]
        },
        {
            "template": "AlternatePrecedence",
            "parameters": [
                [
                    "Activity B"
                ],
                [
                    "Activity L"
                ]
            ]
        },
        {
            "template": "AlternatePrecedence",
            "parameters": [
                [
                    "Activity K"
                ],
                [
                    "SILENT_24"
                ]
            ]
        },
        {
            "template": "AlternatePrecedence",
            "parameters": [
                [
                    "SILENT_29"
                ],
                [
                    "Activity G"
                ]
            ]
        },
        {
            "template": "AlternatePrecedence",
            "parameters": [
                [
                    "Activity G"
                ],
                [
                    "SILENT_31"
                ]
            ]
        },
        {
            "template": "AlternatePrecedence",
            "parameters": [
                [
                    "Activity S"
                ],
                [
                    "SILENT_26"
                ]
            ]
        },
        {
            "template": "AlternatePrecedence",
            "parameters": [
                [
                    "Activity U"
                ],
                [
                    "SILENT_28"
                ]
            ]
        },
        {
            "template": "AlternatePrecedence",
            "parameters": [
                [
                    "SILENT_26"
                ],
                [
                    "Activity M"
                ]
            ]
        },
        {
            "template": "AlternatePrecedence",
            "parameters": [
                [
                    "Activity D"
                ],
                [
                    "SILENT_29"
                ]
            ]
        },
        {
            "template": "AlternatePrecedence",
            "parameters": [
                [
                    "SILENT_23"
                ],
                [
                    "Activity C"
                ]
            ]
        },
        {
            "template": "AlternatePrecedence",
            "parameters": [
                [
                    "Activity A"
                ],
                [
                    "SILENT_23"
                ]
            ]
        },
        {
            "template": "AlternatePrecedence",
            "parameters": [
                [
                    "SILENT_24"
                ],
                [
                    "Activity B"
                ]
            ]
        },
        {
            "template": "AlternatePrecedence",
            "parameters": [
                [
                    "SILENT_25"
                ],
                [
                    "Activity R"
                ]
            ]
        },
        {
            "template": "AlternatePrecedence",
            "parameters": [
                [
                    "SILENT_25"
                ],
                [
                    "Activity N"
                ]
            ]
        },
        {
            "template": "AlternatePrecedence",
            "parameters": [
                [
                    "SILENT_31"
                ],
                [
                    "Activity E"
                ]
            ]
        },
        {
            "template": "AlternatePrecedence",
            "parameters": [
                [
                    "Activity R"
                ],
                [
                    "SILENT_27"
                ]
            ]
        },
        {
            "template": "AlternatePrecedence",
            "parameters": [
                [
                    "Activity P"
                ],
                [
                    "Activity Q"
                ]
            ]
        },
        {
            "template": "AlternatePrecedence",
            "parameters": [
                [
                    "Activity P"
                ],
                [
                    "Activity O"
                ]
            ]
        },
        {
            "template": "AlternatePrecedence",
            "parameters": [
                [
                    "SILENT_23"
                ],
                [
                    "Activity D"
                ]
            ]
        },
        {
            "template": "AlternatePrecedence",
            "parameters": [
                [
                    "Activity J"
                ],
                [
                    "Activity K"
                ]
            ]
        },
        {
            "template": "AlternatePrecedence",
            "parameters": [
                [
                    "Activity N",
                    "Activity Q"
                ],
                [
                    "Activity P"
                ]
            ]
        },
        {
            "template": "AlternatePrecedence",
            "parameters": [
                [
                    "Activity L"
                ],
                [
                    "SILENT_25"
                ]
            ]
        },
        {
            "template": "AlternatePrecedence",
            "parameters": [
                [
                    "SILENT_23"
                ],
                [
                    "Activity J"
                ]
            ]
        },
        {
            "template": "AlternatePrecedence",
            "parameters": [
                [
                    "SILENT_29"
                ],
                [
                    "Activity H"
                ]
            ]
        },
        {
            "template": "AlternatePrecedence",
            "parameters": [
                [
                    "SILENT_29"
                ],
                [
                    "Activity I"
                ]
            ]
        },
        {
            "template": "AlternatePrecedence",
            "parameters": [
                [
                    "SILENT_27"
                ],
                [
                    "Activity T"
                ]
            ]
        },
        {
            "template": "AlternatePrecedence",
            "parameters": [
                [
                    "SILENT_28"
                ],
                [
                    "Activity S"
                ]
            ]
        },
        {
            "template": "AlternatePrecedence",
            "parameters": [
                [
                    "SILENT_29"
                ],
                [
                    "Activity F"
                ]
            ]
        },
        {
            "template": "AlternatePrecedence",
            "parameters": [
                [
                    "SILENT_27"
                ],
                [
                    "Activity U"
                ]
            ]
        },
        {
            "template": "AlternateResponse",
            "parameters": [
                [
                    "Activity B"
                ],
                [
                    "Activity L"
                ]
            ]
        },
        {
            "template": "AlternateResponse",
            "parameters": [
                [
                    "Activity C"
                ],
                [
                    "t_24"
                ]
            ]
        },
        {
            "template": "AlternateResponse",
            "parameters": [
                [
                    "t_29"
                ],
                [
                    "Activity F"
                ]
            ]
        },
        {
            "template": "AlternateResponse",
            "parameters": [
                [
                    "Activity F"
                ],
                [
                    "t_31"
                ]
            ]
        },
        {
            "template": "AlternateResponse",
            "parameters": [
                [
                    "Activity O"
                ],
                [
                    "t_26"
                ]
            ]
        },
        {
            "template": "AlternateResponse",
            "parameters": [
                [
                    "Activity T"
                ],
                [
                    "t_28"
                ]
            ]
        },
        {
            "template": "AlternateResponse",
            "parameters": [
                [
                    "t_26"
                ],
                [
                    "Activity M"
                ]
            ]
        },
        {
            "template": "AlternateResponse",
            "parameters": [
                [
                    "Activity H"
                ],
                [
                    "t_31"
                ]
            ]
        },
        {
            "template": "AlternateResponse",
            "parameters": [
                [
                    "Activity D"
                ],
                [
                    "t_29"
                ]
            ]
        },
        {
            "template": "AlternateResponse",
            "parameters": [
                [
                    "t_23"
                ],
                [
                    "Activity J"
                ]
            ]
        },
        {
            "template": "AlternateResponse",
            "parameters": [
                [
                    "Activity A"
                ],
                [
                    "t_23"
                ]
            ]
        },
        {
            "template": "AlternateResponse",
            "parameters": [
                [
                    "t_24"
                ],
                [
                    "Activity B"
                ]
            ]
        },
        {
            "template": "AlternateResponse",
            "parameters": [
                [
                    "Activity E"
                ],
                [
                    "t_24"
                ]
            ]
        },
        {
            "template": "AlternateResponse",
            "parameters": [
                [
                    "t_25"
                ],
                [
                    "Activity N"
                ]
            ]
        },
        {
            "template": "AlternateResponse",
            "parameters": [
                [
                    "Activity I"
                ],
                [
                    "t_31"
                ]
            ]
        },
        {
            "template": "AlternateResponse",
            "parameters": [
                [
                    "Activity U"
                ],
                [
                    "t_28"
                ]
            ]
        },
        {
            "template": "AlternateResponse",
            "parameters": [
                [
                    "t_31"
                ],
                [
                    "Activity E"
                ]
            ]
        },
        {
            "template": "AlternateResponse",
            "parameters": [
                [
                    "Activity R"
                ],
                [
                    "t_27"
                ]
            ]
        },
        {
            "template": "AlternateResponse",
            "parameters": [
                [
                    "Activity P"
                ],
                [
                    "Activity Q",
                    "Activity O"
                ]
            ]
        },
        {
            "template": "AlternateResponse",
            "parameters": [
                [
                    "Activity K"
                ],
                [
                    "t_24"
                ]
            ]
        },
        {
            "template": "AlternateResponse",
            "parameters": [
                [
                    "Activity J"
                ],
                [
                    "Activity K"
                ]
            ]
        },
        {
            "template": "AlternateResponse",
            "parameters": [
                [
                    "Activity N"
                ],
                [
                    "Activity P"
                ]
            ]
        },
        {
            "template": "AlternateResponse",
            "parameters": [
                [
                    "Activity Q"
                ],
                [
                    "Activity P"
                ]
            ]
        },
        {
            "template": "AlternateResponse",
            "parameters": [
                [
                    "Activity L"
                ],
                [
                    "t_25"
                ]
            ]
        },
        {
            "template": "AlternateResponse",
            "parameters": [
                [
                    "Activity S"
                ],
                [
                    "t_26"
                ]
            ]
        },
        {
            "template": "AlternateResponse",
            "parameters": [
                [
                    "Activity G"
                ],
                [
                    "t_31"
                ]
            ]
        },
        {
            "template": "AlternateResponse",
            "parameters": [
                [
                    "t_27"
                ],
                [
                    "Activity U"
                ]
            ]
        },
        {
            "template": "AlternateResponse",
            "parameters": [
                [
                    "t_28"
                ],
                [
                    "Activity S"
                ]
            ]
        }
    ]
}